YTDPersian/__init__.py
YTDPersian/download.py
YTDPersian-1.0.10.dist-info/LICENSE
YTDPersian-1.0.10.dist-info/METADATA
YTDPersian-1.0.10.dist-info/WHEEL
YTDPersian-1.0.10.dist-info/top_level.txt
YTDPersian-1.0.10.dist-info/RECORD
